LICENSE
MANIFEST.in
README.rst
setup.py
parsimonious/__init__.py
parsimonious/exceptions.py
parsimonious/expressions.py
parsimonious/grammar.py
parsimonious/nodes.py
parsimonious/utils.py
parsimonious.egg-info/PKG-INFO
parsimonious.egg-info/SOURCES.txt
parsimonious.egg-info/dependency_links.txt
parsimonious.egg-info/top_level.txt
parsimonious/tests/__init__.py
parsimonious/tests/benchmarks.py
parsimonious/tests/test_benchmarks.py
parsimonious/tests/test_expressions.py
parsimonious/tests/test_grammar.py
parsimonious/tests/test_nodes.py