Metadata-Version: 1.1
Name: parsimonious
Version: 0.5
Summary: (Soon to be) the fastest pure-Python PEG parser I could muster
Home-page: https://github.com/erikrose/parsimonious
Author: Erik Rose
Author-email: erikrose@grinchcentral.com
License: MIT
Keywords: parse,parser,parsing,peg,packrat,grammar,language
Platform: UNKNOWN
Classifier: Intended Audience :: Developers
Classifier: Natural Language :: English
Classifier: Development Status :: 3 - Alpha
Classifier: License :: OSI Approved :: MIT License
Classifier: Operating System :: OS Independent
Classifier: Programming Language :: Python :: 2
Classifier: Programming Language :: Python :: 2.6
Classifier: Programming Language :: Python :: 2.7
Classifier: Programming Language :: Python :: 3
Classifier: Programming Language :: Python :: 3.1
Classifier: Programming Language :: Python :: 3.2
Classifier: Programming Language :: Python :: 3.3
Classifier: Topic :: Scientific/Engineering :: Information Analysis
Classifier: Topic :: Software Development :: Libraries
Classifier: Topic :: Text Processing :: General
